elegy/__init__.py
elegy/callbacks/__init__.py
elegy/callbacks/callback.py
elegy/callbacks/callback_list.py
elegy/callbacks/csv_logger.py
elegy/callbacks/early_stopping.py
elegy/callbacks/history.py
elegy/callbacks/lambda_callback.py
elegy/callbacks/model_checkpoint.py
elegy/callbacks/progbar_logger.py
elegy/callbacks/remote_monitor.py
elegy/callbacks/sigint.py
elegy/callbacks/tensorboard.py
elegy/callbacks/terminate_nan.py
elegy/callbacks/wandb_callback.py
elegy/data/__init__.py
elegy/data/array_adapter.py
elegy/data/data_adapter.py
elegy/data/data_handler.py
elegy/data/dataset.py
elegy/data/generator_adapter.py
elegy/data/list_adapter.py
elegy/data/tf_dataset_adapter.py
elegy/data/torch_dataloader_adapter.py
elegy/data/utils.py
elegy/model/__init__.py
elegy/model/model.py
elegy/model/model_base.py
elegy/model/model_core.py
elegy/model/utils.py
elegy/nets/__init__.py
elegy/nets/resnet.py
elegy/types.py
elegy/utils.py
elegy-0.8.6.dist-info/LICENSE
elegy-0.8.6.dist-info/WHEEL
elegy-0.8.6.dist-info/METADATA
elegy-0.8.6.dist-info/RECORD
