Metadata-Version: 2.1
Name: elegy
Version: 0.8.6
Summary: Elegy is a Neural Networks framework based on Jax and Haiku.
Home-page: https://poets-ai.github.io/elegy
License: APACHE
Author: Cristian Garcia
Author-email: cgarcia.e88@gmail.com
Requires-Python: >=3.7,<3.10
Classifier: License :: Other/Proprietary License
Classifier: Programming Language :: Python :: 3
Classifier: Programming Language :: Python :: 3.7
Classifier: Programming Language :: Python :: 3.8
Classifier: Programming Language :: Python :: 3.9
Provides-Extra: wandb
Requires-Dist: cloudpickle (>=1.5.0,<2.0.0)
Requires-Dist: tensorboardx (>=2.1,<3.0)
Requires-Dist: treex (>=0.6.5,<0.7.0)
Requires-Dist: wandb (>=0.12.10,<0.13.0)
Project-URL: Repository, https://github.com/poets-ai/elegy
